fig_html/__init__.py
fig_html/fig_html_maker.py
fig_html/utils/__init__.py
fig_html/utils/path.py
fig_html/utils/sample_fig_maker.py
tests/__init__.py
tests/test_all.py
fig_html-0.0.1.dist-info/LICENSE
fig_html-0.0.1.dist-info/METADATA
fig_html-0.0.1.dist-info/WHEEL
fig_html-0.0.1.dist-info/top_level.txt
fig_html-0.0.1.dist-info/RECORD
