Metadata-Version: 2.1
Name: fig-html
Version: 0.0.1
Summary: html generator following directory structure you saved figures
Home-page: https://github.com/kazetof/fig_html
Author: Kazeto Fukasawa
Author-email: fukasawakaze@gmail.com
License: MIT
Keywords: python data-science data-analysis
Platform: UNKNOWN
Classifier: License :: OSI Approved :: MIT License
Classifier: Programming Language :: Python
Classifier: Programming Language :: Python :: 3.6
Classifier: Programming Language :: Python :: 3.7
Classifier: Intended Audience :: Science/Research
Classifier: Intended Audience :: Developers
Classifier: Topic :: Software Development :: Libraries :: Python Modules
Requires-Dist: numpy
Requires-Dist: pandas
Requires-Dist: jinja2 (>=2.10)
Requires-Dist: matplotlib
